CHANGELOG.md
LICENSE
MANIFEST.in
README.md
setup.py
nzme_skynet/__init__.py
nzme_skynet.egg-info/PKG-INFO
nzme_skynet.egg-info/SOURCES.txt
nzme_skynet.egg-info/dependency_links.txt
nzme_skynet.egg-info/entry_points.txt
nzme_skynet.egg-info/requires.txt
nzme_skynet.egg-info/top_level.txt
nzme_skynet.egg-info/zip-safe
nzme_skynet/core/__init__.py
nzme_skynet/core/api/__init__.py
nzme_skynet/core/api/apiclient.py
nzme_skynet/core/api/apiconnection.py
nzme_skynet/core/api/helper.py
nzme_skynet/core/api/resource.py
nzme_skynet/core/bdd/__init__.py
nzme_skynet/core/bdd/basetest.py
nzme_skynet/core/controls/__init__.py
nzme_skynet/core/controls/baseelement.py
nzme_skynet/core/controls/button.py
nzme_skynet/core/controls/checkbox.py
nzme_skynet/core/controls/clickable.py
nzme_skynet/core/controls/clickabletext.py
nzme_skynet/core/controls/element.py
nzme_skynet/core/controls/image.py
nzme_skynet/core/controls/melement.py
nzme_skynet/core/controls/radiobutton.py
nzme_skynet/core/controls/select.py
nzme_skynet/core/controls/table.py
nzme_skynet/core/controls/text.py
nzme_skynet/core/controls/textinput.py
nzme_skynet/core/controls/textlink.py
nzme_skynet/core/controls/enums/__init__.py
nzme_skynet/core/controls/enums/checkboxstates.py
nzme_skynet/core/controls/enums/timeouts.py
nzme_skynet/core/driver/__init__.py
nzme_skynet/core/driver/basedriver.py
nzme_skynet/core/driver/driverfactory.py
nzme_skynet/core/driver/driverregistry.py
nzme_skynet/core/driver/enums/__init__.py
nzme_skynet/core/driver/enums/drivertypes.py
nzme_skynet/core/driver/mobile/__init__.py
nzme_skynet/core/driver/mobile/mobiledriver.py
nzme_skynet/core/driver/mobile/app/__init__.py
nzme_skynet/core/driver/mobile/app/androidappdriver.py
nzme_skynet/core/driver/mobile/app/iosappdriver.py
nzme_skynet/core/driver/mobile/app/mappdriver.py
nzme_skynet/core/driver/mobile/browser/__init__.py
nzme_skynet/core/driver/mobile/browser/androidbrowserdriver.py
nzme_skynet/core/driver/mobile/browser/iosbrowserdriver.py
nzme_skynet/core/driver/mobile/browser/mbrowserdriver.py
nzme_skynet/core/driver/web/__init__.py
nzme_skynet/core/driver/web/browserdriver.py
nzme_skynet/core/driver/web/browsers/__init__.py
nzme_skynet/core/driver/web/browsers/chrome.py
