Metadata-Version: 2.1
Name: nzme-skynet
Version: 0.5.0
Summary: NZME Test Automation Library
Home-page: https://github.com/MilindThakur/nzme-skynet
Author: Milind Thakur
Author-email: milindat28@gmail.com
Maintainer: milindat28@gmail.com
License: BSD 3-Clause License
Keywords: selenium,bdd,appium,browser automation,mobile automation
Platform: UNKNOWN
Classifier: Development Status :: 4 - Beta
Classifier: Environment :: Web Environment
Classifier: Intended Audience :: Developers
Classifier: Topic :: Internet
Classifier: Topic :: Scientific/Engineering
Classifier: Topic :: Software Development
Classifier: Topic :: Software Development :: Quality Assurance
Classifier: Topic :: Software Development :: Testing
Classifier: Topic :: Software Development :: Testing :: Acceptance
Classifier: Operating System :: OS Independent
Classifier: Programming Language :: Python :: 2.7
Classifier: Programming Language :: Python :: 3.6
Classifier: Programming Language :: Python :: 3.7
